{
    "os": "Linux-5.14.0-284.40.1.el9_2.x86_64-x86_64-with-glibc2.10",
    "python": "3.8.3",
    "heartbeatAt": "2024-05-10T09:40:42.551795",
    "startedAt": "2024-05-10T09:40:41.548094",
    "docker": null,
    "cuda": null,
    "args": [
        "../nerf-pytorch/data/nerf_synthetic/lego",
        "--workspace",
        "trial_nerf",
        "-O",
        "--bound",
        "1.0",
        "--scale",
        "0.8",
        "--dt_gamma",
        "0"
    ],
    "state": "running",
    "program": "profile_ngp.py",
    "codePathLocal": "profile_ngp.py",
    "codePath": "profile_ngp.py",
    "git": {
        "remote": "https://github.com/ashawkey/torch-ngp.git",
        "commit": "b6e080468925f0bb44827b4f8f0ed08291dcf8a9"
    },
    "email": "buereddyvarunireddy@gmail.com",
    "root": "/scratch/vb2386/Documents/torch-ngp",
    "host": "gr042.hpc.nyu.edu",
    "username": "vb2386",
    "executable": "/scratch/vb2386/Documents/torch-ngp/venv/bin/python",
    "cpu_count": 25,
    "cpu_count_logical": 48,
    "cpu_freq": {
        "current": 3500.9880833333336,
        "min": 1200.0,
        "max": 3900.0
    },
    "cpu_freq_per_core": [
        {
            "current": 3500.001,
            "min": 1200.0,
            "max": 3900.0
        },
        {
            "current": 3500.639,
            "min": 1200.0,
            "max": 3900.0
        },
        {
            "current": 3500.112,
            "min": 1200.0,
            "max": 3900.0
        },
        {
            "current": 3516.797,
            "min": 1200.0,
            "max": 3900.0
        },
        {
            "current": 3499.946,
            "min": 1200.0,
            "max": 3900.0
        },
        {
            "current": 3500.262,
            "min": 1200.0,
            "max": 3900.0
        },
        {
            "current": 3501.226,
            "min": 1200.0,
            "max": 3900.0
        },
        {
            "current": 3500.252,
            "min": 1200.0,
            "max": 3900.0
        },
        {
            "current": 3507.737,
            "min": 1200.0,
            "max": 3900.0
        },
        {
            "current": 3508.553,
            "min": 1200.0,
            "max": 3900.0
        },
        {
            "current": 3501.352,
            "min": 1200.0,
            "max": 3900.0
        },
        {
            "current": 3500.149,
            "min": 1200.0,
            "max": 3900.0
        },
        {
            "current": 3500.317,
            "min": 1200.0,
            "max": 3900.0
        },
        {
            "current": 3500.033,
            "min": 1200.0,
            "max": 3900.0
        },
        {
            "current": 3499.026,
            "min": 1200.0,
            "max": 3900.0
        },
        {
            "current": 3500.026,
            "min": 1200.0,
            "max": 3900.0
        },
        {
            "current": 3500.0,
            "min": 1200.0,
            "max": 3900.0
        },
        {
            "current": 3500.043,
            "min": 1200.0,
            "max": 3900.0
        },
        {
            "current": 3499.814,
            "min": 1200.0,
            "max": 3900.0
        },
        {
            "current": 3494.552,
            "min": 1200.0,
            "max": 3900.0
        },
        {
            "current": 3497.623,
            "min": 1200.0,
            "max": 3900.0
        },
        {
            "current": 3511.21,
            "min": 1200.0,
            "max": 3900.0
        },
        {
            "current": 3492.154,
            "min": 1200.0,
            "max": 3900.0
        },
        {
            "current": 3500.075,
            "min": 1200.0,
            "max": 3900.0
        },
        {
            "current": 3500.094,
            "min": 1200.0,
            "max": 3900.0
        },
        {
            "current": 3499.999,
            "min": 1200.0,
            "max": 3900.0
        },
        {
            "current": 3499.999,
            "min": 1200.0,
            "max": 3900.0
        },
        {
            "current": 3500.001,
            "min": 1200.0,
            "max": 3900.0
        },
        {
            "current": 3500.002,
            "min": 1200.0,
            "max": 3900.0
        },
        {
            "current": 3499.999,
            "min": 1200.0,
            "max": 3900.0
        },
        {
            "current": 3500.0,
            "min": 1200.0,
            "max": 3900.0
        },
        {
            "current": 3500.002,
            "min": 1200.0,
            "max": 3900.0
        },
        {
            "current": 3500.0,
            "min": 1200.0,
            "max": 3900.0
        },
        {
            "current": 3500.0,
            "min": 1200.0,
            "max": 3900.0
        },
        {
            "current": 3500.001,
            "min": 1200.0,
            "max": 3900.0
        },
        {
            "current": 3499.999,
            "min": 1200.0,
            "max": 3900.0
        },
        {
            "current": 3499.999,
            "min": 1200.0,
            "max": 3900.0
        },
        {
            "current": 3499.999,
            "min": 1200.0,
            "max": 3900.0
        },
        {
            "current": 3500.002,
            "min": 1200.0,
            "max": 3900.0
        },
        {
            "current": 3499.999,
            "min": 1200.0,
            "max": 3900.0
        },
        {
            "current": 3499.998,
            "min": 1200.0,
            "max": 3900.0
        },
        {
            "current": 3500.186,
            "min": 1200.0,
            "max": 3900.0
        },
        {
            "current": 3500.393,
            "min": 1200.0,
            "max": 3900.0
        },
        {
            "current": 3499.715,
            "min": 1200.0,
            "max": 3900.0
        },
        {
            "current": 3510.656,
            "min": 1200.0,
            "max": 3900.0
        },
        {
            "current": 3507.921,
            "min": 1200.0,
            "max": 3900.0
        },
        {
            "current": 3499.851,
            "min": 1200.0,
            "max": 3900.0
        },
        {
            "current": 3498.177,
            "min": 1200.0,
            "max": 3900.0
        }
    ],
    "disk": {
        "/": {
            "total": 78.08685302734375,
            "used": 21.374736785888672
        }
    },
    "gpu": "Quadro RTX 8000",
    "gpu_count": 1,
    "gpu_devices": [
        {
            "name": "Quadro RTX 8000",
            "memory_total": 48318382080
        }
    ],
    "memory": {
        "total": 377.06226348876953
    }
}
